CHANGES.rst
DEVELOP.rst
MANIFEST.in
README.rst
bootstrap.sh
requirements.txt
setup.cfg
setup.py
docs/LICENSE.GPL
docs/LICENSE.txt
src/webcouturier/__init__.py
src/webcouturier.dropdownmenu.egg-info/PKG-INFO
src/webcouturier.dropdownmenu.egg-info/SOURCES.txt
src/webcouturier.dropdownmenu.egg-info/dependency_links.txt
src/webcouturier.dropdownmenu.egg-info/entry_points.txt
src/webcouturier.dropdownmenu.egg-info/namespace_packages.txt
src/webcouturier.dropdownmenu.egg-info/not-zip-safe
src/webcouturier.dropdownmenu.egg-info/requires.txt
src/webcouturier.dropdownmenu.egg-info/top_level.txt
src/webcouturier/dropdownmenu/__init__.py
src/webcouturier/dropdownmenu/configure.zcml
src/webcouturier/dropdownmenu/setuphandlers.py
src/webcouturier/dropdownmenu/testing.py
src/webcouturier/dropdownmenu/upgrades.py
src/webcouturier/dropdownmenu/upgrades.zcml
src/webcouturier/dropdownmenu/browser/__init__.py
src/webcouturier/dropdownmenu/browser/configure.zcml
src/webcouturier/dropdownmenu/browser/controlpanel.py
src/webcouturier/dropdownmenu/browser/dropdown.py
src/webcouturier/dropdownmenu/browser/dropdown_recurse.pt
src/webcouturier/dropdownmenu/browser/dropdown_sections.pt
src/webcouturier/dropdownmenu/browser/interfaces.py
src/webcouturier/dropdownmenu/browser/static/dropdown.js
src/webcouturier/dropdownmenu/browser/static/dropdown.less
src/webcouturier/dropdownmenu/browser/static/dropdownmenu-compiled.css
src/webcouturier/dropdownmenu/browser/static/dropdownmenu-compiled.css.map
src/webcouturier/dropdownmenu/browser/static/dropdownmenu-compiled.js
src/webcouturier/dropdownmenu/browser/static/dropdownmenu-compiled.js.map
src/webcouturier/dropdownmenu/locales/plone.pot
src/webcouturier/dropdownmenu/locales/rebuild_i18n
src/webcouturier/dropdownmenu/locales/webcouturier.dropdownmenu.pot
src/webcouturier/dropdownmenu/locales/de/LC_MESSAGES/webcouturier.dropdownmenu.po
src/webcouturier/dropdownmenu/locales/es/LC_MESSAGES/plone.po
src/webcouturier/dropdownmenu/locales/es/LC_MESSAGES/webcouturier.dropdownmenu.po
src/webcouturier/dropdownmenu/locales/pt_BR/LC_MESSAGES/plone.po
src/webcouturier/dropdownmenu/locales/pt_BR/LC_MESSAGES/webcouturier.dropdownmenu.po
src/webcouturier/dropdownmenu/locales/zh_CN/LC_MESSAGES/webcouturier.dropdownmenu.po
src/webcouturier/dropdownmenu/profiles/default/browserlayer.xml
src/webcouturier/dropdownmenu/profiles/default/controlpanel.xml
