Metadata-Version: 1.1
Name: webcouturier.dropdownmenu
Version: 3.0.2
Summary: Dropdown menus for global navigation in Plone
Home-page: http://plone.org/products/webcouturier-dropdownmenu
Author: Denys Mishunov
Author-email: denys.mishunov@gmail.com
License: GPL
Keywords: web couturier dropdown menu navigation
Platform: UNKNOWN
Classifier: Development Status :: 5 - Production/Stable
Classifier: Environment :: Web Environment
Classifier: Framework :: Plone :: 5.0
Classifier: Framework :: Plone :: 5.1
Classifier: Framework :: Plone
Classifier: License :: OSI Approved :: GNU General Public License (GPL)
Classifier: Operating System :: OS Independent
Classifier: Programming Language :: Python :: 2.7
Classifier: Programming Language :: Python
Classifier: Topic :: Software Development :: Libraries :: Python Modules
